glesys/__init__.py
glesys/__main__.py
glesys/configuration.py
glesys/exceptions.py
glesys/helpers.py
glesys/output.py
glesys/session.py
glesys/workers.py
glesys/api/__init__.py
glesys/api/dns.py
glesys/api/ip.py
glesys/api/server.py
glesys/cli/args.py
glesys/cli/args_router.py
glesys/cli/ip.py
glesys/cli/server.py
glesys/cli/arguments/dns.py
glesys/cli/arguments/ip.py
glesys/cli/arguments/letsencrypt.py
glesys/cli/arguments/server.py
glesys/dns/cli_handler.py
glesys/hooks/letsencrypt/__init__.py
glesys/hooks/letsencrypt/cli_handler.py
glesys/models/configuration.py
glesys-0.2.dist-info/LICENSE
glesys-0.2.dist-info/METADATA
glesys-0.2.dist-info/WHEEL
glesys-0.2.dist-info/entry_points.txt
glesys-0.2.dist-info/top_level.txt
glesys-0.2.dist-info/RECORD
