Metadata-Version: 2.1
Name: glesys
Version: 0.2
Summary: A SDK/helper library to work with Glesys API.
Author-email: Anton Hvornum <anton@hvornum.se>
License: AGPL-1.0-or-later
Project-URL: Home, https://api.glesys.com/
Project-URL: Documentation, https://glesys.se/kb/artikel/api-dokumentation
Project-URL: Source, https://github.com/Torxed/python-glesys
Keywords: linux,glesys,server,oauth2,openid,connect
Classifier: Programming Language :: Python :: 3.10
Classifier: Operating System :: POSIX :: Linux
Requires-Python: >=3.10
License-File: LICENSE
Requires-Dist: pydantic
Requires-Dist: toml
Provides-Extra: doc
Requires-Dist: sphinx ; extra == 'doc'
Requires-Dist: sphinx-rtd-theme ; extra == 'doc'
Provides-Extra: letsencrypt
Requires-Dist: acme (>=0.29.0) ; extra == 'letsencrypt'
Requires-Dist: certbot (>=0.34.0) ; extra == 'letsencrypt'
Requires-Dist: zope ; extra == 'letsencrypt'
